{
  "sourcePdf": "2025 OCR ASME SECT II MATERIALS PART A SA-451 TO END.pdf",
  "sourcePageNumber": 99,
  "globalPageIndex": 897,
  "width": 620.16,
  "height": 798.0,
  "text": "L \nASME BPVC.II.A-2025 \nTABLE A1.2 Heat Treatment Requirements \nDesignationrrype TemperatureA \nAustenitic (Chromium-Nickel) (Chromium-Nickel-Manganese) \nAll Cr-Ni steels except as listed below \n302,308,309,309Cb,310,310Cb,S21640,S30215,S30452, \nS30615, S31740, S32615,S33228, S33425, S35140,S38100, \nS38815 \n304H,309H,310H,316H \n309HCb, 310HCb, 321H, 347H, 348H \nCold Worked \nHot Finished \nN08020 \nN08367 \nN08700, N08904, S35115 \nN08810, S31277 \nN08811,N08925,S31025,S31254,S31266,S32050,S32654 \nN08926,S35315 \nS20161 \nS20431,S20432,S20433,S30530 \nS30600, S30601 \nS30616 \nS31060 \nS31727, S32053 \nS33228 \nS33426 \nS33550 \nS34565 \nS34752 \nS31200,S31803,S32001,S32550 \nS31260 \nS32003, S82011 \nS32101 \nS32202 \nS32205 \nS32304 \nS32506 \nS32520 \nS32750\u00a3 \nS32760 \nS32808, S39274 \nS32900 \nS32906 \nS32950 \nS44537 \nS81921 \nS82012,S82031,S82441 \nS82013, S82121 \nS82122 \nA Minimum, unless otherwise indicated. \n1900 \u00b0F [1040 \u00b0CJ \n1900 \u00b0F [1040 \u00b0CJ \n1900 \u00b0F [1040 \u00b0CJ \n2000 \u00b0F [1095 \u00b0CJ \n1925 \u00b0F [1050 \u00b0CJ \n1700 to 1850 \u00b0F [925 to 1010 \u00b0CJ \n2025 \u00b0F [1105 \u00b0CJ \n2000 \u00b0F [1095 \u00b0C] \n2050 'F [1120 \u00b0CJ \n2100 \u00b0F [1150 \u00b0CJ \n2010 \u00b0F [1100 \u00b0CJ \n1900 to 2000 \u00b0F [1040 to 1095 \u00b0C) \n1900 to 2010 \u00b0F [1040 to 1100 \u00b0CJ \n2010 to 2140 'F [1100 to 1170 \u00b0CJ \n1920 to 2100 'F [1050 to 1150 \u00b0CJ \n1975 to 2160 \u00b0F [1080 to 1180 \u00b0CJ \n1975 to 2155 \u00b0F [1080 to 1180 \u00b0CJ \n2050 to 2160 \u00b0F [1120 to 1180 \u00b0CJ \n1925 to 2100 \u00b0F (1050 to 1150 \u00b0CJ \n2065 to 2155 \u00b0F (1130 to 1180 \u00b0CJ \n2050 to 2140 \u00b0F (1120 to 1170 'CJ \n1940 to 2140 \u00b0F [1060 to 1170 \u00b0CJ \nDuplex (Austenitic-Ferritic) \n1900 \u00b0F (1040 \u00b0CJ \n1870 to 2010 \u00b0F [1020 to 1100 \u00b0CJ \n1850 \u00b0F [1010 \u00b0CJ \n1870 \u00b0F [1020 \u00b0CJ \n1800 to 1975 \u00b0F (980 to 1080 \u00b0CJ \n1900 \u00b0F (1040 \u00b0CJ \n1800 'F [980 \u00b0CJ \n1870 to 2050 \u00b0F (1020 to 1120 \u00b0CJ \n1975 to 2050 \u00b0F (1080 to 1120 \u00b0CJ \n1880 to 2060 \u00b0F (1025 to 1125 \u00b0CJ \n2010 \u00b0F [1100 \u00b0CJ \n1925 to 2100 \u00b0F (1050 to 1150 \u00b0CJ \n1750 \u00b1 25 'F [955 \u00b1 15 \u00b0CJ \n1900 to 2100 \u00b0F [1040 to 1150 \u00b0CJ \n1850 \u00b1 25 'F [1010 \u00b1 15 \u00b0CJ \n1922 \u00b0F (1050 \u00b0CJ \n1760 to 201 o \u00b0F [960 to 1100 'CJ \n1830 \u00b0F [1000 \u00b0CJ \n1830 to 2010 'F [1000 to 1100 \u00b0CJ \n1725 \u00b0F (940 \u00b0CJ \nSA-480/SA-480M (ASTM A480/A480M) \nCooling/Testing Requirements \nB \nC \nC \nC \nC \nC \nC \nC \nC \nC \nC \nC \nC \nC \nC \nC \nC \nC \nC \nC \nC \nC \nC \nC \nC \nC \nC \nD \nC \nC \nC \nC \nC \nC \nC \nC \nC \nC \nC \nC \nC \nC \n8 Quenched in water or rapidly cooled by other means at a rate sufficient to prevent reprecipitation of carbides, as demonstrable by the capability of passing the test for \nresistance to intergranular corrosion specified in 18.2. \nc Quenched in water or rapidly cooled by other means. \n0 Quenched in water, except that coiled product heat treated in a continuous annealing line shall be water quenched or rapidly cooled by other means. \nE Temperatures above 2060 \u00b0F are permissible if the resulting microstructure provides the properties required by this specification or any additional requirements of the \npurchase order. \n795 ",
  "words": [],
  "tableCount": 0,
  "noteCount": 0,
  "tabulaTablesPath": "tables_tabula/page-0897.json",
  "tabulaTablesCsv": "tables_tabula/page-0897.csv",
  "tabulaTableCount": 1,
  "bestTextPath": "best_text/pages/page-0897.txt",
  "bestTextSource": "pass1",
  "bestTextLength": 2894,
  "bestTextAlphaRatio": 0.3832
}